myaws/__init__.py
myaws/aws_helper.py
mylogging/__init__.py
mylogging/logger.py
common_py_lib-1.7.0.dist-info/LICENSE
common_py_lib-1.7.0.dist-info/METADATA
common_py_lib-1.7.0.dist-info/WHEEL
common_py_lib-1.7.0.dist-info/top_level.txt
common_py_lib-1.7.0.dist-info/RECORD
