Metadata-Version: 2.1
Name: common-py-lib
Version: 1.7.0
Summary: Python Library
Author: Steve Zheng
Author-email: steve.zheng@gmail.com
License: MIT
Classifier: Programming Language :: Python :: 3
Classifier: License :: OSI Approved :: MIT License
Classifier: Operating System :: OS Independent
License-File: LICENSE
Requires-Dist: boto3 (>=1.26.0)
Requires-Dist: botocore (>=1.29.0)
Requires-Dist: jmespath (>=1.0.1)
Requires-Dist: python-dateutil (>=2.8.2)
Requires-Dist: s3transfer (>=0.6.0)
Requires-Dist: six (>=1.16.0)
Requires-Dist: urllib3 (>=1.26.12)
